realdebrid/__init__.py
realdebrid/data.py
realdebrid/exceptions.py
realdebrid/realdebrid.py
realdebrid/typings.py
pyrd-2.0.0.dist-info/LICENSE
pyrd-2.0.0.dist-info/METADATA
pyrd-2.0.0.dist-info/WHEEL
pyrd-2.0.0.dist-info/RECORD
