Metadata-Version: 2.1
Name: pyrd
Version: 2.0.0
Summary: Real-Debrid API bindings for Python
Home-page: https://github.com/itsnebulalol/pyrd
License: MIT
Author: Dominic Frye
Author-email: me@itsnebula.net
Requires-Python: >=3.11,<4.0
Classifier: Intended Audience :: Developers
Classifier: License :: OSI Approved :: MIT License
Classifier: Natural Language :: English
Classifier: Operating System :: OS Independent
Classifier: Programming Language :: Python
Classifier: Programming Language :: Python :: 3
Classifier: Programming Language :: Python :: 3.11
Classifier: Programming Language :: Python :: 3.12
Classifier: Programming Language :: Python :: 3 :: Only
Classifier: Programming Language :: Python :: 3.13
Classifier: Topic :: Software Development
Classifier: Topic :: Utilities
Classifier: Typing :: Typed
Requires-Dist: aiohttp (>=3.9.5,<4.0.0)
Project-URL: Repository, https://github.com/itsnebulalol/pyrd
